bluetooth_data_tools/__init__.py
bluetooth_data_tools/_time_impl.c
bluetooth_data_tools/_time_impl.cpython-312-aarch64-linux-musl.so
bluetooth_data_tools/_time_impl.pyx
bluetooth_data_tools/_utils_impl.c
bluetooth_data_tools/_utils_impl.cpython-312-aarch64-linux-musl.so
bluetooth_data_tools/_utils_impl.pyx
bluetooth_data_tools/distance.py
bluetooth_data_tools/gap.c
bluetooth_data_tools/gap.cpython-312-aarch64-linux-musl.so
bluetooth_data_tools/gap.pxd
bluetooth_data_tools/gap.py
bluetooth_data_tools/privacy.py
bluetooth_data_tools/py.typed
bluetooth_data_tools/time.py
bluetooth_data_tools/utils.c
bluetooth_data_tools/utils.cpython-312-aarch64-linux-musl.so
bluetooth_data_tools/utils.pxd
bluetooth_data_tools/utils.py
bluetooth_data_tools/utils_wrapper.h
bluetooth_data_tools-1.28.2.dist-info/LICENSE
bluetooth_data_tools-1.28.2.dist-info/METADATA
bluetooth_data_tools-1.28.2.dist-info/WHEEL
bluetooth_data_tools-1.28.2.dist-info/RECORD
