Metadata-Version: 2.3
Name: bluetooth-data-tools
Version: 1.28.2
Summary: Tools for converting bluetooth data and packets
License: Apache-2.0
Author: J. Nick Koston
Author-email: nick@koston.org
Requires-Python: >=3.10
Classifier: Development Status :: 5 - Production/Stable
Classifier: Intended Audience :: Developers
Classifier: License :: OSI Approved :: Apache Software License
Classifier: Natural Language :: English
Classifier: Operating System :: OS Independent
Classifier: Programming Language :: Python :: 3
Classifier: Programming Language :: Python :: 3.10
Classifier: Programming Language :: Python :: 3.11
Classifier: Programming Language :: Python :: 3.12
Classifier: Programming Language :: Python :: 3.13
Classifier: Topic :: Software Development :: Libraries
Provides-Extra: docs
Requires-Dist: Sphinx (>=5,<9) ; extra == "docs"
Requires-Dist: cryptography (>=41.0.3)
Requires-Dist: myst-parser (>=0.18,<4.1) ; extra == "docs"
Requires-Dist: sphinx-rtd-theme (>=1,<4) ; extra == "docs"
Project-URL: Bug Tracker, https://github.com/bdraco/bluetooth-data-tools/issues
Project-URL: Changelog, https://github.com/bdraco/bluetooth-data-tools/blob/main/CHANGELOG.md
Project-URL: Documentation, https://bluetooth-data-tools.readthedocs.io
Project-URL: Repository, https://github.com/bdraco/bluetooth-data-tools
